djangoldp_branding/__init__.py
djangoldp_branding/apps.py
djangoldp_branding/djangoldp_settings.py
djangoldp_branding/djangoldp_urls.py
djangoldp_branding/processor.py
djangoldp_branding/views.py
djangoldp_branding/locale/en/LC_MESSAGES/django.mo
djangoldp_branding/locale/en/LC_MESSAGES/django.po
djangoldp_branding/locale/es/LC_MESSAGES/django.mo
djangoldp_branding/locale/es/LC_MESSAGES/django.po
djangoldp_branding/locale/fr/LC_MESSAGES/django.mo
djangoldp_branding/locale/fr/LC_MESSAGES/django.po
djangoldp_branding/static/css/admin.css
djangoldp_branding/static/css/main.css
djangoldp_branding/static/images/favicon.webp
djangoldp_branding/templates/__init__.py
djangoldp_branding/templates/base.html
djangoldp_branding/templates/base_email.html
djangoldp_branding/templates/email.html
djangoldp_branding/templates/accessrequests/access_requested.html
djangoldp_branding/templates/accessrequests/access_resolved.html
djangoldp_branding/templates/admin/base.html
djangoldp_branding/templates/admin/login.html
djangoldp_branding/templates/django_registration/activation_complete.html
djangoldp_branding/templates/django_registration/activation_failed.html
djangoldp_branding/templates/django_registration/registration_closed.html
djangoldp_branding/templates/django_registration/registration_complete.html
djangoldp_branding/templates/django_registration/registration_form.html
djangoldp_branding/templates/joboffer/email.html
djangoldp_branding/templates/oidc_provider/authorize.html
djangoldp_branding/templates/password/email.html
djangoldp_branding/templates/registration/activate.html
djangoldp_branding/templates/registration/activation_complete.html
djangoldp_branding/templates/registration/logged_out.html
djangoldp_branding/templates/registration/login.html
djangoldp_branding/templates/registration/logout.html
djangoldp_branding/templates/registration/lost_user.html
djangoldp_branding/templates/registration/password_change_done.html
djangoldp_branding-3.0.0.dist-info/METADATA
djangoldp_branding-3.0.0.dist-info/WHEEL
djangoldp_branding-3.0.0.dist-info/top_level.txt
djangoldp_branding-3.0.0.dist-info/RECORD
